ebranch/__init__.py
ebranch/__main__.py
ebranch/bugzilla.py
ebranch/cli.py
ebranch/dependencies.py
ebranch/dnf.py
ebranch/pagure.py
ebranch/tests/__init__.py
ebranch/tests/test_dnf.py
ebranch/tests/test_pagure.py
ebranch-0.0.3.dist-info/AUTHORS
ebranch-0.0.3.dist-info/COPYING.md
ebranch-0.0.3.dist-info/METADATA
ebranch-0.0.3.dist-info/WHEEL
ebranch-0.0.3.dist-info/entry_points.txt
ebranch-0.0.3.dist-info/top_level.txt
ebranch-0.0.3.dist-info/RECORD
