Metadata-Version: 2.1
Name: ebranch
Version: 0.0.3
Summary: Tool for branching Fedora packages for EPEL
Home-page: https://pagure.io/epel/ebranch
Author: Michel Alexandre Salim
Author-email: salimma@fedoraproject.org
License: GPLv2+
Classifier: Development Status :: 3 - Alpha
Classifier: Environment :: Console
Classifier: License :: OSI Approved :: GNU General Public License v2 or later (GPLv2+)
License-File: COPYING.md
License-File: AUTHORS
Requires-Dist: click
Requires-Dist: networkx
Requires-Dist: requests
Provides-Extra: dev
Requires-Dist: black ; extra == 'dev'
Requires-Dist: build ; extra == 'dev'
Requires-Dist: pip-tools ; extra == 'dev'
Requires-Dist: pytest ; extra == 'dev'
Requires-Dist: pytest-cov ; extra == 'dev'
Provides-Extra: test
Requires-Dist: pytest ; extra == 'test'
